elyra_streamlit_extension-0.1.0.data/data/etc/jupyter/jupyter_notebook_config.d/streamlit_extension.json
elyra_streamlit_extension-0.1.0.data/data/etc/jupyter/jupyter_server_config.d/streamlit_extension.json
elyra_streamlit_extension-0.1.0.data/data/share/jupyter/labextensions/@elyra/streamlit-extension/build_log.json
elyra_streamlit_extension-0.1.0.data/data/share/jupyter/labextensions/@elyra/streamlit-extension/install.json
elyra_streamlit_extension-0.1.0.data/data/share/jupyter/labextensions/@elyra/streamlit-extension/package.json
elyra_streamlit_extension-0.1.0.data/data/share/jupyter/labextensions/@elyra/streamlit-extension/static/lib_index_js.acce5f2769653c15d0ba.js
elyra_streamlit_extension-0.1.0.data/data/share/jupyter/labextensions/@elyra/streamlit-extension/static/lib_index_js.acce5f2769653c15d0ba.js.map
elyra_streamlit_extension-0.1.0.data/data/share/jupyter/labextensions/@elyra/streamlit-extension/static/remoteEntry.6c3d9a48883461171e6f.js
elyra_streamlit_extension-0.1.0.data/data/share/jupyter/labextensions/@elyra/streamlit-extension/static/remoteEntry.6c3d9a48883461171e6f.js.map
elyra_streamlit_extension-0.1.0.data/data/share/jupyter/labextensions/@elyra/streamlit-extension/static/style.js
elyra_streamlit_extension-0.1.0.data/data/share/jupyter/labextensions/@elyra/streamlit-extension/static/style_index_js.b12be0c3321e0f412d04.js
elyra_streamlit_extension-0.1.0.data/data/share/jupyter/labextensions/@elyra/streamlit-extension/static/style_index_js.b12be0c3321e0f412d04.js.map
elyra_streamlit_extension-0.1.0.data/data/share/jupyter/labextensions/@elyra/streamlit-extension/static/vendors-node_modules_css-loader_dist_runtime_api_js-node_modules_css-loader_dist_runtime_cssW-72eba1.0b4e2fd41fc7cf53ca74.js
elyra_streamlit_extension-0.1.0.data/data/share/jupyter/labextensions/@elyra/streamlit-extension/static/vendors-node_modules_css-loader_dist_runtime_api_js-node_modules_css-loader_dist_runtime_cssW-72eba1.0b4e2fd41fc7cf53ca74.js.map
elyra_streamlit_extension-0.1.0.dist-info/LICENSE
elyra_streamlit_extension-0.1.0.dist-info/METADATA
elyra_streamlit_extension-0.1.0.dist-info/WHEEL
elyra_streamlit_extension-0.1.0.dist-info/top_level.txt
elyra_streamlit_extension-0.1.0.dist-info/RECORD
