Metadata-Version: 2.1
Name: elyra-streamlit-extension
Version: 0.1.0
Summary: An extension to open a streamlit app within JupyterLab
Home-page: https://github.com/elyra-ai/streamlit-extension
Author: Elyra Authors
License: Apache-2.0
Keywords: Jupyter,JupyterLab,JupyterLab3
Platform: Linux
Platform: Mac OS X
Platform: Windows
Classifier: License :: OSI Approved :: Apache Software License
Classifier: Programming Language :: Python
Classifier: Programming Language :: Python :: 3
Classifier: Programming Language :: Python :: 3.7
Classifier: Programming Language :: Python :: 3.8
Classifier: Programming Language :: Python :: 3.9
Classifier: Programming Language :: Python :: 3.10
Classifier: Framework :: Jupyter
Classifier: Framework :: Jupyter :: JupyterLab
Classifier: Framework :: Jupyter :: JupyterLab :: 3
Classifier: Framework :: Jupyter :: JupyterLab :: Extensions
Classifier: Framework :: Jupyter :: JupyterLab :: Extensions :: Prebuilt
Requires-Python: >=3.7
License-File: LICENSE
Requires-Dist: jupyter-server (<2,>=1.6)
Requires-Dist: jupyter-server-proxy
Requires-Dist: streamlit
